lambda_pkg_resources/__init__.py
lambda_pkg_resources-0.0.6.dist-info/LICENSE
lambda_pkg_resources-0.0.6.dist-info/METADATA
lambda_pkg_resources-0.0.6.dist-info/WHEEL
lambda_pkg_resources-0.0.6.dist-info/top_level.txt
lambda_pkg_resources-0.0.6.dist-info/RECORD
