Metadata-Version: 2.1
Name: lambda-pkg-resources
Version: 0.0.6
Summary: Supports a dist-info installation of packages with package exclusions
Home-page: https://github.com/QuiNovas/lambda-pkg-resources
Author: Joseph Wortmann
Author-email: joseph.wortmann@gmail.com
License: APL 2.0
Keywords: pkg_resources extension
Platform: UNKNOWN
Classifier: Development Status :: 4 - Beta
Classifier: Intended Audience :: Developers
Classifier: Topic :: Software Development :: Libraries :: Python Modules
Classifier: License :: OSI Approved :: Apache Software License
Classifier: Programming Language :: Python :: 3.8
License-File: LICENSE
Requires-Dist: setuptools
Requires-Dist: pip
Requires-Dist: wheel
